{
    "ds": "./ds.h5",
    "figs": {},
    "results": {
        "q0": {
            "0": {
                "raw": {
                    "Bloch vector": [
                        0.0132,
                        0.0194,
                        0.6558
                    ],
                    "density matrix": "./arrays.npz#results.q0.0.raw.density matrix",
                    "fidelity": 0.8279000000000001,
                    "trace_distance": 0.17249944927448313
                },
                "mitigated": {
                    "Bloch vector": "./arrays.npz#results.q0.0.mitigated.Bloch vector",
                    "density matrix": "./arrays.npz#results.q0.0.mitigated.density matrix",
                    "fidelity": 0.9987043772110695,
                    "trace_distance": 0.035994760576094686
                }
            },
            "1": {
                "raw": {
                    "Bloch vector": [
                        0.2698,
                        0.0174,
                        -0.5992
                    ],
                    "density matrix": "./arrays.npz#results.q0.1.raw.density matrix",
                    "fidelity": 0.7996,
                    "trace_distance": 0.24173096615866158
                },
                "mitigated": {
                    "Bloch vector": "./arrays.npz#results.q0.1.mitigated.Bloch vector",
                    "density matrix": "./arrays.npz#results.q0.1.mitigated.density matrix",
                    "fidelity": 0.9464113639309453,
                    "trace_distance": 0.2277579443548594
                }
            },
            "+": {
                "raw": {
                    "Bloch vector": [
                        0.5962,
                        0.038,
                        -0.1576
                    ],
                    "density matrix": "./arrays.npz#results.q0.+.raw.density matrix",
                    "fidelity": 0.7981,
                    "trace_distance": 0.21756389865968112
                },
                "mitigated": {
                    "Bloch vector": "./arrays.npz#results.q0.+.mitigated.Bloch vector",
                    "density matrix": "./arrays.npz#results.q0.+.mitigated.density matrix",
                    "fidelity": 0.9698773205942344,
                    "trace_distance": 0.12007554105964467
                }
            },
            "i+": {
                "raw": {
                    "Bloch vector": [
                        -0.0522,
                        0.6236,
                        -0.15
                    ],
                    "density matrix": "./arrays.npz#results.q0.i+.raw.density matrix",
                    "fidelity": 0.8118,
                    "trace_distance": 0.20426808365478932
                },
                "mitigated": {
                    "Bloch vector": "./arrays.npz#results.q0.i+.mitigated.Bloch vector",
                    "density matrix": "./arrays.npz#results.q0.i+.mitigated.density matrix",
                    "fidelity": 0.9887451926475216,
                    "trace_distance": 0.10608867683442161
                }
            },
            "quantum information": {
                "raw": {
                    "ptm": "./arrays.npz#results.q0.quantum information.raw.ptm",
                    "superoperator": "./arrays.npz#results.q0.quantum information.raw.superoperator",
                    "choi": "./arrays.npz#results.q0.quantum information.raw.choi",
                    "negativity": 0.3679185714886335,
                    "Quantum Memory Robustness": 0.363860639236099,
                    "fidelity": 0.9253367434120015
                },
                "mitigated": {
                    "ptm": "./arrays.npz#results.q0.quantum information.mitigated.ptm",
                    "superoperator": "./arrays.npz#results.q0.quantum information.mitigated.superoperator",
                    "choi": "./arrays.npz#results.q0.quantum information.mitigated.choi",
                    "negativity": 0.820106735688232,
                    "Quantum Memory Robustness": 0.8120657309003694,
                    "fidelity": 0.9445866117784264
                }
            }
        }
    },
    "figs_q0_0": "./figs_q0_0.png",
    "figs_q0_1": "./figs_q0_1.png",
    "figs_q0_+": "./figs_q0_+.png",
    "figs_q0_i+": "./figs_q0_i+.png",
    "initial_parameters": {
        "qubits": [
            "q0"
        ],
        "num_runs": 10000,
        "reset_type_thermal_or_active": "active",
        "flux_point_joint_or_independent": "joint",
        "simulate": false,
        "simulation_duration_ns": 2500,
        "timeout": 100,
        "load_data_id": null,
        "multiplexed": false,
        "desired_state": [
            [
                0.0,
                0.0
            ],
            [
                3.141592653589793,
                0.0
            ],
            [
                1.5707963267948966,
                0.0
            ],
            [
                1.5707963267948966,
                1.5707963267948966
            ]
        ],
        "operation_name": "id",
        "alpha": 1.16
    }
}