{
    "ds": "./ds.h5",
    "figs": {},
    "results": {
        "q0": {
            "0": {
                "raw": {
                    "Bloch vector": [
                        0.1068,
                        0.135,
                        0.444
                    ],
                    "density matrix": "./arrays.npz#results.q0.0.raw.density matrix",
                    "fidelity": 0.722,
                    "trace_distance": 0.29101857329043457
                },
                "mitigated": {
                    "Bloch vector": "./arrays.npz#results.q0.0.mitigated.Bloch vector",
                    "density matrix": "./arrays.npz#results.q0.0.mitigated.density matrix",
                    "fidelity": 0.8788592874571297,
                    "trace_distance": 0.22227769634866615
                }
            },
            "1": {
                "raw": {
                    "Bloch vector": [
                        -0.0248,
                        -0.0862,
                        -0.3528
                    ],
                    "density matrix": "./arrays.npz#results.q0.1.raw.density matrix",
                    "fidelity": 0.6764,
                    "trace_distance": 0.32669302104575176
                },
                "mitigated": {
                    "Bloch vector": "./arrays.npz#results.q0.1.mitigated.Bloch vector",
                    "density matrix": "./arrays.npz#results.q0.1.mitigated.density matrix",
                    "fidelity": 0.7318428801037099,
                    "trace_distance": 0.2702775674058113
                }
            },
            "+": {
                "raw": {
                    "Bloch vector": [
                        -0.2202,
                        -0.0056,
                        0.0054
                    ],
                    "density matrix": "./arrays.npz#results.q0.+.raw.density matrix",
                    "fidelity": 0.3899,
                    "trace_distance": 0.6101123994806203
                },
                "mitigated": {
                    "Bloch vector": "./arrays.npz#results.q0.+.mitigated.Bloch vector",
                    "density matrix": "./arrays.npz#results.q0.+.mitigated.density matrix",
                    "fidelity": 0.3696810430706068,
                    "trace_distance": 0.6326811481771352
                }
            },
            "i+": {
                "raw": {
                    "Bloch vector": [
                        -0.002,
                        -0.193,
                        0.0076
                    ],
                    "density matrix": "./arrays.npz#results.q0.i+.raw.density matrix",
                    "fidelity": 0.40349999999999997,
                    "trace_distance": 0.5965129420222164
                },
                "mitigated": {
                    "Bloch vector": "./arrays.npz#results.q0.i+.mitigated.Bloch vector",
                    "density matrix": "./arrays.npz#results.q0.i+.mitigated.density matrix",
                    "fidelity": 0.3899952251855502,
                    "trace_distance": 0.6127249997854582
                }
            },
            "quantum information": {
                "raw": {
                    "ptm": "./arrays.npz#results.q0.quantum information.raw.ptm",
                    "superoperator": "./arrays.npz#results.q0.quantum information.raw.superoperator",
                    "choi": "./arrays.npz#results.q0.quantum information.raw.choi",
                    "negativity": -0.0,
                    "Quantum Memory Robustness": 0.0,
                    "fidelity": 0.40321361665614736
                },
                "mitigated": {
                    "ptm": "./arrays.npz#results.q0.quantum information.mitigated.ptm",
                    "superoperator": "./arrays.npz#results.q0.quantum information.mitigated.superoperator",
                    "choi": "./arrays.npz#results.q0.quantum information.mitigated.choi",
                    "negativity": 0.17668849014615415,
                    "Quantum Memory Robustness": 0.17668849005086518,
                    "fidelity": 0.33069232311313485
                }
            }
        }
    },
    "figs_q0_0": "./figs_q0_0.png",
    "figs_q0_1": "./figs_q0_1.png",
    "figs_q0_+": "./figs_q0_+.png",
    "figs_q0_i+": "./figs_q0_i+.png",
    "initial_parameters": {
        "qubits": [
            "q0"
        ],
        "num_runs": 10000,
        "reset_type_thermal_or_active": "active",
        "flux_point_joint_or_independent": "joint",
        "simulate": false,
        "simulation_duration_ns": 2500,
        "interaction_start_time_in_ns": 0,
        "interaction_end_time_in_ns": 153,
        "interaction_time_in_ns": 54,
        "compensation": true,
        "timeout": 100,
        "load_data_id": null,
        "multiplexed": false,
        "desired_state": [
            [
                0,
                0
            ],
            [
                3.141592653589793,
                0
            ],
            [
                1.5707963267948966,
                0
            ],
            [
                1.5707963267948966,
                1.5707963267948966
            ]
        ],
        "operation_name": "id"
    }
}