{
    "ds": "./ds.h5",
    "figs": {},
    "results": {
        "q0": {
            "gst_results": {
                "TP": {
                    "rho0": {
                        "density_mx": "./arrays.npz#results.q0.gst_results.TP.rho0.density_mx",
                        "fidelity": 0.8186981491069051
                    },
                    "meas_op": {
                        "0": {
                            "povm": "./arrays.npz#results.q0.gst_results.TP.meas_op.0.povm",
                            "fidelity": 0.9406343686704708
                        },
                        "1": {
                            "povm": "./arrays.npz#results.q0.gst_results.TP.meas_op.1.povm",
                            "fidelity": 0.9260651646692678
                        }
                    },
                    "gate_op": {
                        "I": {
                            "choi": "./arrays.npz#results.q0.gst_results.TP.gate_op.I.choi",
                            "fidelity": 0.986391346301343,
                            "robustness": 0.9728400276193081
                        },
                        "x90": {
                            "choi": "./arrays.npz#results.q0.gst_results.TP.gate_op.x90.choi",
                            "fidelity": 0.998709596871838,
                            "robustness": 0.9976979347145067
                        },
                        "y90": {
                            "choi": "./arrays.npz#results.q0.gst_results.TP.gate_op.y90.choi",
                            "fidelity": 0.9984178680332733,
                            "robustness": 0.9971999221546013
                        }
                    }
                },
                "CPTP": {
                    "rho0": {
                        "density_mx": "./arrays.npz#results.q0.gst_results.CPTP.rho0.density_mx",
                        "fidelity": 0.7980522089708096
                    },
                    "meas_op": {
                        "0": {
                            "povm": "./arrays.npz#results.q0.gst_results.CPTP.meas_op.0.povm",
                            "fidelity": 0.9582910024346007
                        },
                        "1": {
                            "povm": "./arrays.npz#results.q0.gst_results.CPTP.meas_op.1.povm",
                            "fidelity": 0.9017948268966146
                        }
                    },
                    "gate_op": {
                        "I": {
                            "choi": "./arrays.npz#results.q0.gst_results.CPTP.gate_op.I.choi",
                            "fidelity": 0.9858886495393052,
                            "robustness": 0.9718359507068048
                        },
                        "x90": {
                            "choi": "./arrays.npz#results.q0.gst_results.CPTP.gate_op.x90.choi",
                            "fidelity": 0.9983137639227533,
                            "robustness": 0.996904554655605
                        },
                        "y90": {
                            "choi": "./arrays.npz#results.q0.gst_results.CPTP.gate_op.y90.choi",
                            "fidelity": 0.9982191878789006,
                            "robustness": 0.9968060377145149
                        }
                    }
                },
                "Ideal": {
                    "rho0": {
                        "density_mx": "./arrays.npz#results.q0.gst_results.Ideal.rho0.density_mx",
                        "fidelity": 0.9999999999999999
                    },
                    "meas_op": {
                        "0": {
                            "povm": "./arrays.npz#results.q0.gst_results.Ideal.meas_op.0.povm",
                            "fidelity": 0.9999999999999999
                        },
                        "1": {
                            "povm": "./arrays.npz#results.q0.gst_results.Ideal.meas_op.1.povm",
                            "fidelity": 1.0000000000000002
                        }
                    },
                    "gate_op": {
                        "I": {
                            "choi": "./arrays.npz#results.q0.gst_results.Ideal.gate_op.I.choi",
                            "fidelity": 1.0,
                            "robustness": 0.9999999999999984
                        },
                        "x90": {
                            "choi": "./arrays.npz#results.q0.gst_results.Ideal.gate_op.x90.choi",
                            "fidelity": 1.0000000000000002,
                            "robustness": 0.9999999960997938
                        },
                        "y90": {
                            "choi": "./arrays.npz#results.q0.gst_results.Ideal.gate_op.y90.choi",
                            "fidelity": 1.0000000000000002,
                            "robustness": 0.9999999960998065
                        }
                    }
                }
            }
        }
    },
    "initial_parameters": {
        "qubits": [
            "q0"
        ],
        "alpha": 1.01,
        "max_circuit_depth_in_power": 4,
        "num_runs": 10000,
        "reset_type_thermal_or_active": "active",
        "flux_point_joint_or_independent": "joint",
        "simulate": false,
        "simulation_duration_ns": 5000,
        "timeout": 100,
        "load_data_id": null,
        "multiplexed": false
    }
}