{
    "ds": "./ds.h5",
    "figs": {},
    "results": {
        "q0": {
            "0": {
                "raw": {
                    "Bloch vector": [
                        0.2194,
                        0.2408,
                        0.5208
                    ],
                    "density matrix": "./arrays.npz#results.q0.0.raw.density matrix",
                    "fidelity": 0.7604,
                    "trace_distance": 0.28972126259561964
                },
                "mitigated": {
                    "Bloch vector": "./arrays.npz#results.q0.0.mitigated.Bloch vector",
                    "density matrix": "./arrays.npz#results.q0.0.mitigated.density matrix",
                    "fidelity": 0.9106223592751677,
                    "trace_distance": 0.2989609351149951
                }
            },
            "1": {
                "raw": {
                    "Bloch vector": [
                        -0.329,
                        -0.3444,
                        -0.4906
                    ],
                    "density matrix": "./arrays.npz#results.q0.1.raw.density matrix",
                    "fidelity": 0.7453,
                    "trace_distance": 0.34869066520341496
                },
                "mitigated": {
                    "Bloch vector": "./arrays.npz#results.q0.1.mitigated.Bloch vector",
                    "density matrix": "./arrays.npz#results.q0.1.mitigated.density matrix",
                    "fidelity": 0.8376026269825606,
                    "trace_distance": 0.35047362109618263
                }
            },
            "+": {
                "raw": {
                    "Bloch vector": [
                        0.0744,
                        -0.036,
                        0.0228
                    ],
                    "density matrix": "./arrays.npz#results.q0.+.raw.density matrix",
                    "fidelity": 0.5371999999999999,
                    "trace_distance": 0.46329018983785963
                },
                "mitigated": {
                    "Bloch vector": "./arrays.npz#results.q0.+.mitigated.Bloch vector",
                    "density matrix": "./arrays.npz#results.q0.+.mitigated.density matrix",
                    "fidelity": 0.5955331505406922,
                    "trace_distance": 0.40846217902419807
                }
            },
            "i+": {
                "raw": {
                    "Bloch vector": [
                        -0.0844,
                        0.114,
                        0.005
                    ],
                    "density matrix": "./arrays.npz#results.q0.i+.raw.density matrix",
                    "fidelity": 0.5569999999999999,
                    "trace_distance": 0.4450124604997033
                },
                "mitigated": {
                    "Bloch vector": "./arrays.npz#results.q0.i+.mitigated.Bloch vector",
                    "density matrix": "./arrays.npz#results.q0.i+.mitigated.density matrix",
                    "fidelity": 0.6260032822532395,
                    "trace_distance": 0.37729454049880523
                }
            },
            "quantum information": {
                "raw": {
                    "ptm": "./arrays.npz#results.q0.quantum information.raw.ptm",
                    "superoperator": "./arrays.npz#results.q0.quantum information.raw.superoperator",
                    "choi": "./arrays.npz#results.q0.quantum information.raw.choi",
                    "negativity": -0.0,
                    "Quantum Memory Robustness": 3.344174492880825e-09,
                    "fidelity": 0.7431229671847442
                },
                "mitigated": {
                    "ptm": "./arrays.npz#results.q0.quantum information.mitigated.ptm",
                    "superoperator": "./arrays.npz#results.q0.quantum information.mitigated.superoperator",
                    "choi": "./arrays.npz#results.q0.quantum information.mitigated.choi",
                    "negativity": 0.17732428047161763,
                    "Quantum Memory Robustness": 0.17732428038234516,
                    "fidelity": 0.7794132900965118
                }
            }
        }
    },
    "figs_q0_0": "./figs_q0_0.png",
    "figs_q0_1": "./figs_q0_1.png",
    "figs_q0_+": "./figs_q0_+.png",
    "figs_q0_i+": "./figs_q0_i+.png",
    "initial_parameters": {
        "qubits": [
            "q0"
        ],
        "num_runs": 10000,
        "reset_type_thermal_or_active": "active",
        "flux_point_joint_or_independent": "joint",
        "simulate": false,
        "simulation_duration_ns": 2500,
        "interaction_start_time_in_ns": 0,
        "interaction_end_time_in_ns": 153,
        "interaction_time_in_ns": 87,
        "compensation": true,
        "timeout": 100,
        "load_data_id": null,
        "multiplexed": false,
        "desired_state": [
            [
                0,
                0
            ],
            [
                3.141592653589793,
                0
            ],
            [
                1.5707963267948966,
                0
            ],
            [
                1.5707963267948966,
                1.5707963267948966
            ]
        ],
        "operation_name": "id"
    }
}