{
    "ds": "./ds.h5",
    "figs": {},
    "results": {
        "q0": {
            "0": {
                "raw": {
                    "Bloch vector": [
                        -0.0086,
                        0.0016,
                        0.7286
                    ],
                    "density matrix": "./arrays.npz#results.q0.0.raw.density matrix",
                    "fidelity": 0.8643000000000001,
                    "trace_distance": 0.13577046807019558
                },
                "mitigated": {
                    "Bloch vector": "./arrays.npz#results.q0.0.mitigated.Bloch vector",
                    "density matrix": "./arrays.npz#results.q0.0.mitigated.density matrix",
                    "fidelity": 0.9996915990234835,
                    "trace_distance": 0.017561348937837923
                }
            },
            "1": {
                "raw": {
                    "Bloch vector": [
                        -0.5774,
                        0.0358,
                        -0.4382
                    ],
                    "density matrix": "./arrays.npz#results.q0.1.raw.density matrix",
                    "fidelity": 0.7191,
                    "trace_distance": 0.4032033109983102
                },
                "mitigated": {
                    "Bloch vector": "./arrays.npz#results.q0.1.mitigated.Bloch vector",
                    "density matrix": "./arrays.npz#results.q0.1.mitigated.density matrix",
                    "fidelity": 0.78251105739896,
                    "trace_distance": 0.4371392680820956
                }
            },
            "+": {
                "raw": {
                    "Bloch vector": [
                        0.6156,
                        -0.0484,
                        -0.3262
                    ],
                    "density matrix": "./arrays.npz#results.q0.+.raw.density matrix",
                    "fidelity": 0.8078000000000001,
                    "trace_distance": 0.25323524636195494
                },
                "mitigated": {
                    "Bloch vector": "./arrays.npz#results.q0.+.mitigated.Bloch vector",
                    "density matrix": "./arrays.npz#results.q0.+.mitigated.density matrix",
                    "fidelity": 0.9318935805771802,
                    "trace_distance": 0.21851075269170167
                }
            },
            "i+": {
                "raw": {
                    "Bloch vector": [
                        0.0118,
                        0.6092,
                        -0.3306
                    ],
                    "density matrix": "./arrays.npz#results.q0.i+.raw.density matrix",
                    "fidelity": 0.8046,
                    "trace_distance": 0.2560079295646914
                },
                "mitigated": {
                    "Bloch vector": "./arrays.npz#results.q0.i+.mitigated.Bloch vector",
                    "density matrix": "./arrays.npz#results.q0.i+.mitigated.density matrix",
                    "fidelity": 0.9275232615218412,
                    "trace_distance": 0.2230639699541056
                }
            },
            "quantum information": {
                "raw": {
                    "ptm": "./arrays.npz#results.q0.quantum information.raw.ptm",
                    "superoperator": "./arrays.npz#results.q0.quantum information.raw.superoperator",
                    "choi": "./arrays.npz#results.q0.quantum information.raw.choi",
                    "negativity": 0.6043700115269656,
                    "Quantum Memory Robustness": 0.6043699909684164,
                    "fidelity": 0.8550545089153118
                },
                "mitigated": {
                    "ptm": "./arrays.npz#results.q0.quantum information.mitigated.ptm",
                    "superoperator": "./arrays.npz#results.q0.quantum information.mitigated.superoperator",
                    "choi": "./arrays.npz#results.q0.quantum information.mitigated.choi",
                    "negativity": 0.8169538997644574,
                    "Quantum Memory Robustness": 0.8169538984089999,
                    "fidelity": 0.8456220086297443
                }
            }
        }
    },
    "figs_q0_0": "./figs_q0_0.png",
    "figs_q0_1": "./figs_q0_1.png",
    "figs_q0_+": "./figs_q0_+.png",
    "figs_q0_i+": "./figs_q0_i+.png",
    "initial_parameters": {
        "qubits": [
            "q0"
        ],
        "alpha": 1.29,
        "num_runs": 10000,
        "reset_type_thermal_or_active": "active",
        "flux_point_joint_or_independent": "joint",
        "simulate": false,
        "simulation_duration_ns": 2500,
        "timeout": 100,
        "load_data_id": null,
        "multiplexed": false,
        "desired_state": [
            [
                0.0,
                0.0
            ],
            [
                3.141592653589793,
                0.0
            ],
            [
                1.5707963267948966,
                0.0
            ],
            [
                1.5707963267948966,
                1.5707963267948966
            ]
        ],
        "operation_name": "id"
    }
}