{
    "ds": "./ds.h5",
    "figs": {},
    "results": {
        "q0": {
            "0": {
                "raw": {
                    "Bloch vector": [
                        0.2206,
                        0.2386,
                        0.4832
                    ],
                    "density matrix": "./arrays.npz#results.q0.0.raw.density matrix",
                    "fidelity": 0.7416,
                    "trace_distance": 0.3052362036194265
                },
                "mitigated": {
                    "Bloch vector": "./arrays.npz#results.q0.0.mitigated.Bloch vector",
                    "density matrix": "./arrays.npz#results.q0.0.mitigated.density matrix",
                    "fidelity": 0.9014988534718515,
                    "trace_distance": 0.3138489230954099
                }
            },
            "1": {
                "raw": {
                    "Bloch vector": [
                        -0.3012,
                        -0.3222,
                        -0.2914
                    ],
                    "density matrix": "./arrays.npz#results.q0.1.raw.density matrix",
                    "fidelity": 0.6456999999999999,
                    "trace_distance": 0.41732728163876365
                },
                "mitigated": {
                    "Bloch vector": "./arrays.npz#results.q0.1.mitigated.Bloch vector",
                    "density matrix": "./arrays.npz#results.q0.1.mitigated.density matrix",
                    "fidelity": 0.684866208801481,
                    "trace_distance": 0.423985075972845
                }
            },
            "+": {
                "raw": {
                    "Bloch vector": [
                        -0.249,
                        -0.155,
                        0.0848
                    ],
                    "density matrix": "./arrays.npz#results.q0.+.raw.density matrix",
                    "fidelity": 0.37549999999999994,
                    "trace_distance": 0.6307172583654264
                },
                "mitigated": {
                    "Bloch vector": "./arrays.npz#results.q0.+.mitigated.Bloch vector",
                    "density matrix": "./arrays.npz#results.q0.+.mitigated.density matrix",
                    "fidelity": 0.3476114593664459,
                    "trace_distance": 0.6654489246412365
                }
            },
            "i+": {
                "raw": {
                    "Bloch vector": [
                        0.0722,
                        -0.2474,
                        0.1392
                    ],
                    "density matrix": "./arrays.npz#results.q0.i+.raw.density matrix",
                    "fidelity": 0.37629999999999997,
                    "trace_distance": 0.6286088290821248
                },
                "mitigated": {
                    "Bloch vector": "./arrays.npz#results.q0.i+.mitigated.Bloch vector",
                    "density matrix": "./arrays.npz#results.q0.i+.mitigated.density matrix",
                    "fidelity": 0.3488373925679049,
                    "trace_distance": 0.6737770127822083
                }
            },
            "quantum information": {
                "raw": {
                    "ptm": "./arrays.npz#results.q0.quantum information.raw.ptm",
                    "superoperator": "./arrays.npz#results.q0.quantum information.raw.superoperator",
                    "choi": "./arrays.npz#results.q0.quantum information.raw.choi",
                    "negativity": -0.0,
                    "Quantum Memory Robustness": 0.0,
                    "fidelity": 0.4078944980806331
                },
                "mitigated": {
                    "ptm": "./arrays.npz#results.q0.quantum information.mitigated.ptm",
                    "superoperator": "./arrays.npz#results.q0.quantum information.mitigated.superoperator",
                    "choi": "./arrays.npz#results.q0.quantum information.mitigated.choi",
                    "negativity": 0.2395727801195025,
                    "Quantum Memory Robustness": 0.23957277039420188,
                    "fidelity": 0.33971322212235644
                }
            }
        }
    },
    "figs_q0_0": "./figs_q0_0.png",
    "figs_q0_1": "./figs_q0_1.png",
    "figs_q0_+": "./figs_q0_+.png",
    "figs_q0_i+": "./figs_q0_i+.png",
    "initial_parameters": {
        "qubits": [
            "q0"
        ],
        "num_runs": 10000,
        "reset_type_thermal_or_active": "active",
        "flux_point_joint_or_independent": "joint",
        "simulate": false,
        "simulation_duration_ns": 2500,
        "interaction_start_time_in_ns": 0,
        "interaction_end_time_in_ns": 153,
        "interaction_time_in_ns": 35,
        "compensation": true,
        "timeout": 100,
        "load_data_id": null,
        "multiplexed": false,
        "desired_state": [
            [
                0,
                0
            ],
            [
                3.141592653589793,
                0
            ],
            [
                1.5707963267948966,
                0
            ],
            [
                1.5707963267948966,
                1.5707963267948966
            ]
        ],
        "operation_name": "id"
    }
}